.gitignore
LICENSE
MANIFEST.in
README.md
setup.cfg
setup.py
bin/ligolw_add
bin/ligolw_combine_segments
bin/ligolw_cut
bin/ligolw_diff
bin/ligolw_print
bin/ligolw_print_tables
bin/ligolw_segment_diff
bin/ligolw_segment_intersect
bin/ligolw_segment_query
bin/ligolw_segment_union
bin/ligolw_segments_from_cats
etc/ligolw.js
etc/ligolw.xsl
etc/ligolw_dtd.txt
misc/__init__.py
misc/__init__.pyc
misc/generate_vcs_info.py
misc/generate_vcs_info.pyc
misc/git_version.py.in
pycbc_glue/LDBDClient.py
pycbc_glue/LDBDWClient.py
pycbc_glue/__init__.py
pycbc_glue/datafind.py
pycbc_glue/git_version.py
pycbc_glue/gpstime.py
pycbc_glue/iterutils.py
pycbc_glue/lal.py
pycbc_glue/ldbd.py
pycbc_glue/markup.py
pycbc_glue/offsetvector.py
pycbc_glue/pidfile.py
pycbc_glue/pipeline.py
pycbc_glue/segments.py
pycbc_glue/segmentsUtils.py
pycbc_glue/text_progress_bar.py
pycbc_glue/utils.py
pycbc_glue/auth/__init__.py
pycbc_glue/auth/saml.py
pycbc_glue/ligolw/__init__.py
pycbc_glue/ligolw/array.py
pycbc_glue/ligolw/dbtables.py
pycbc_glue/ligolw/ilwd.c
pycbc_glue/ligolw/ilwd.h
pycbc_glue/ligolw/ilwd.py
pycbc_glue/ligolw/ligolw.py
pycbc_glue/ligolw/lsctables.py
pycbc_glue/ligolw/param.py
pycbc_glue/ligolw/table.py
pycbc_glue/ligolw/tokenizer.RowBuilder.c
pycbc_glue/ligolw/tokenizer.RowDumper.c
pycbc_glue/ligolw/tokenizer.Tokenizer.c
pycbc_glue/ligolw/tokenizer.c
pycbc_glue/ligolw/tokenizer.h
pycbc_glue/ligolw/types.py
pycbc_glue/ligolw/utils/__init__.py
pycbc_glue/ligolw/utils/coalesce_db.py
pycbc_glue/ligolw/utils/coincs.py
pycbc_glue/ligolw/utils/ligolw_add.py
pycbc_glue/ligolw/utils/ligolw_sqlite.py
pycbc_glue/ligolw/utils/print_tables.py
pycbc_glue/ligolw/utils/process.py
pycbc_glue/ligolw/utils/search_summary.py
pycbc_glue/ligolw/utils/segments.py
pycbc_glue/ligolw/utils/time_slide.py
pycbc_glue/segmentdb/__init__.py
pycbc_glue/segmentdb/logic.py
pycbc_glue/segmentdb/query_engine.py
pycbc_glue/segmentdb/segmentdb_utils.py
pycbc_glue_obsolete.egg-info/PKG-INFO
pycbc_glue_obsolete.egg-info/SOURCES.txt
pycbc_glue_obsolete.egg-info/dependency_links.txt
pycbc_glue_obsolete.egg-info/top_level.txt
src/segments/infinity.c
src/segments/segment.c
src/segments/segmentlist.c
