Metadata-Version: 1.1
Name: pycbc-glue-obsolete
Version: 1.1.0
Summary: Grid LSC User Engine
Home-page: https://github.com/ligo-cbc/pycbc-glue
Author: Duncan Brown
Author-email: duncan.brown@ligo.org
License: See file LICENSE
Download-URL: https://github.com/ligo-cbc/pycbc-glue/archive/v1.1.0.tar.gz
Platform: UNKNOWN
